settrie.cp39-win_amd64.pyd
settrie/settrie.cpp
settrie/settrie.pyx
pysettrie-1.0.2.dist-info/LICENSE
pysettrie-1.0.2.dist-info/METADATA
pysettrie-1.0.2.dist-info/WHEEL
pysettrie-1.0.2.dist-info/top_level.txt
pysettrie-1.0.2.dist-info/RECORD
