Metadata-Version: 2.1
Name: pysettrie
Version: 1.0.2
Summary: pysettrie package
Home-page: https://github.com/GregoryMorse/pysettrie
Author: Gregory Morse and Márton Miháltz
Author-email: Gregory Morse <gregory.morse@live.com>, Márton Miháltz <mihaltz.marton@nytud.mta.hu>
Project-URL: Homepage, https://github.com/GregoryMorse/pysettrie
Project-URL: Issues, https://github.com/GregoryMorse/pysettrie/issues
Classifier: Programming Language :: Python :: 3
Classifier: License :: OSI Approved :: GNU Lesser General Public License v3 (LGPLv3)
Classifier: Operating System :: OS Independent
Requires-Python: >=3.5
License-File: LICENSE
